swmmanywhere/__init__.py
swmmanywhere/__main__.py
swmmanywhere/filepaths.py
swmmanywhere/geospatial_utilities.py
swmmanywhere/graph_utilities.py
swmmanywhere/logging.py
swmmanywhere/metric_utilities.py
swmmanywhere/parameters.py
swmmanywhere/post_processing.py
swmmanywhere/prepare_data.py
swmmanywhere/preprocessing.py
swmmanywhere/shortest_path_utils.py
swmmanywhere/swmmanywhere.py
swmmanywhere/utilities.py
swmmanywhere/defs/basic_drainage_all_bits.inp
swmmanywhere/defs/demo_config.yml
swmmanywhere/defs/iso_converter.yml
swmmanywhere/defs/schema.yml
swmmanywhere/defs/storm.dat
swmmanywhere/defs/swmm_conversion.yml
swmmanywhere/examples/data.py
swmmanywhere/examples/demo_graph.json
swmmanywhere/graphfcns/__init__.py
swmmanywhere/graphfcns/design_graphfcns.py
swmmanywhere/graphfcns/network_cleaning_graphfcns.py
swmmanywhere/graphfcns/outfall_graphfcns.py
swmmanywhere/graphfcns/subcatchment_graphfcns.py
swmmanywhere/graphfcns/topology_graphfcns.py
swmmanywhere/misc/debug_derive_rc.py
swmmanywhere/misc/debug_metrics.py
swmmanywhere/misc/debug_topology.py
swmmanywhere-0.1.1.dist-info/METADATA
swmmanywhere-0.1.1.dist-info/WHEEL
swmmanywhere-0.1.1.dist-info/licenses/LICENSE
swmmanywhere-0.1.1.dist-info/RECORD
