Metadata-Version: 2.3
Name: swmmanywhere
Version: 0.1.1
Summary: SWMManywhere software
Project-URL: Documentation, https://imperialcollegelondon.github.io/SWMManywhere/
Project-URL: Issues, https://github.com/ImperialCollegeLondon/SWMManywhere/issues
Project-URL: Source, https://github.com/ImperialCollegeLondon/SWMManywhere
Author-email: Barnaby Dobson <b.dobson@imperial.ac.uk>, Imperial College London RSE Team <ict-rse-team@imperial.ac.uk>
License-File: LICENSE
Classifier: Development Status :: 4 - Beta
Classifier: Intended Audience :: Science/Research
Classifier: License :: OSI Approved :: MIT License
Classifier: Operating System :: OS Independent
Classifier: Programming Language :: Python
Classifier: Programming Language :: Python :: 3 :: Only
Classifier: Programming Language :: Python :: 3.10
Classifier: Programming Language :: Python :: 3.11
Classifier: Programming Language :: Python :: 3.12
Classifier: Topic :: Scientific/Engineering
Classifier: Topic :: Scientific/Engineering :: GIS
Classifier: Typing :: Typed
Requires-Python: >=3.10
Requires-Dist: cdsapi
Requires-Dist: cytoolz
Requires-Dist: geopandas>=1
Requires-Dist: geopy
Requires-Dist: joblib
Requires-Dist: jsonschema
Requires-Dist: loguru
Requires-Dist: netcdf4
Requires-Dist: networkx>=3
Requires-Dist: numpy>=2
Requires-Dist: osmnx>=1.9.3
Requires-Dist: pandas
Requires-Dist: planetary-computer
Requires-Dist: pyarrow
Requires-Dist: pydantic
Requires-Dist: pyflwdir
Requires-Dist: pystac-client
Requires-Dist: pyswmm
Requires-Dist: pywbt>=0.2.2
Requires-Dist: pyyaml
Requires-Dist: rasterio
Requires-Dist: rioxarray
Requires-Dist: scipy
Requires-Dist: shapely
Requires-Dist: tqdm
Requires-Dist: xarray
Provides-Extra: dev
Requires-Dist: mypy; extra == 'dev'
Requires-Dist: pip-tools; extra == 'dev'
Requires-Dist: pre-commit; extra == 'dev'
Requires-Dist: pytest; extra == 'dev'
Requires-Dist: pytest-cov; extra == 'dev'
Requires-Dist: pytest-mock; extra == 'dev'
Requires-Dist: pytest-mypy; extra == 'dev'
Requires-Dist: ruff; extra == 'dev'
Provides-Extra: doc
Requires-Dist: mkdocs; extra == 'doc'
Requires-Dist: mkdocs-coverage; extra == 'doc'
Requires-Dist: mkdocs-include-markdown-plugin; extra == 'doc'
Requires-Dist: mkdocs-jupyter; extra == 'doc'
Requires-Dist: mkdocs-material; extra == 'doc'
Requires-Dist: mkdocs-material-extensions; extra == 'doc'
Requires-Dist: mkdocstrings[python]; extra == 'doc'
